app/__init__.py
app/error_handling.py
app/helper.py
app/inputData.py
app/inputDataUtils.py
app/result.py
app/utils.py
app/components/__init__.py
app/components/joint.py
app/components/load.py
app/components/member.py
app/components/node.py
app/components/section_material.py
app/components/shell.py
app/components/solid.py
app/components/spring.py
app/components/support.py
fem/__init__.py
fem/boundary_condition.py
fem/error_log.py
fem/file_io.py
fem/material.py
fem/mesh.py
fem/model.py
fem/result_processor.py
fem/section.py
fem/solver.py
fem/stiffness_matrix.py
fem/strain_stress.py
fem/vtk_writer.py
fem/elements/__init__.py
fem/elements/advanced_element.py
fem/elements/bar_element.py
fem/elements/base_element.py
fem/elements/nonlinear_bar_element.py
fem/elements/shell_element.py
fem/elements/solid_element.py
fem/models/__init__.py
fem/models/fa_beam.py
fem/models/fa_joint.py
fem/models/fa_load.py
fem/models/fa_material.py
fem/models/fa_node.py
fem/models/fa_section.py
fem/models/fa_shell.py
fem/models/fa_solid.py
fem/models/fa_spring.py
fem/models/fa_support.py
fem/models/fa_thickness.py
fem/nonlinear/__init__.py
fem/nonlinear/nonlinear_solver.py
fem/nonlinear/hysteresis/__init__.py
fem/nonlinear/hysteresis/base_hysteresis.py
fem/nonlinear/hysteresis/jr_stiffness_reduction.py
fempython-1.0.2.dist-info/METADATA
fempython-1.0.2.dist-info/WHEEL
fempython-1.0.2.dist-info/licenses/LICENSE
fempython-1.0.2.dist-info/RECORD
