Metadata-Version: 2.4
Name: FEMPython
Version: 1.0.2
Summary: Python FEM解析モジュール
Author: StructuralEngine
License-Expression: MIT
License-File: LICENSE
Requires-Python: >=3.11
Requires-Dist: flask>=3.0.3
Requires-Dist: functions-framework>=3.8.1
Requires-Dist: js2py
Requires-Dist: numpy>=2.1.0
Requires-Dist: scipy>=1.14.1
Provides-Extra: dev
Requires-Dist: flet>=0.23.2; extra == 'dev'
Requires-Dist: pytest>=8.3.2; extra == 'dev'
